datalab_on_jupyter/.gitignore
datalab_on_jupyter/Untitled.ipynb
datalab_on_jupyter/__init__.py
datalab_on_jupyter/_version.py
datalab_on_jupyter/are-you-happy-now.ipynb
datalab_on_jupyter/config.py
datalab_on_jupyter/example.ipynb
datalab_on_jupyter/extension.py
datalab_on_jupyter/handlers.py
datalab_on_jupyter/index.html
datalab_on_jupyter/nteractapp.py
datalab_on_jupyter/package.json
datalab_on_jupyter/semver.py
datalab_on_jupyter/tsconfig.json
datalab_on_jupyter/utils.py
datalab_on_jupyter/webpack.config.js
datalab_on_jupyter/yarn.lock
datalab_on_jupyter/.ipynb_checkpoints/Untitled-checkpoint.ipynb
datalab_on_jupyter/.ipynb_checkpoints/are-you-happy-now-checkpoint.ipynb
datalab_on_jupyter/.ipynb_checkpoints/example-checkpoint.ipynb
datalab_on_jupyter/app/app.tsx
datalab_on_jupyter/app/bootstrap.tsx
datalab_on_jupyter/app/config.tsx
datalab_on_jupyter/app/fonts.ts
datalab_on_jupyter/app/globals.d.ts
datalab_on_jupyter/app/index.tsx
datalab_on_jupyter/app/store.ts
datalab_on_jupyter/app/components/editable-title-overlay.tsx
datalab_on_jupyter/app/components/last-saved.tsx
datalab_on_jupyter/app/components/nav.tsx
datalab_on_jupyter/app/components/themed-logo.tsx
datalab_on_jupyter/app/contents/directory.tsx
datalab_on_jupyter/app/contents/headers.tsx
datalab_on_jupyter/app/contents/index.tsx
datalab_on_jupyter/app/contents/notebook.tsx
datalab_on_jupyter/app/contents/file/index.tsx
datalab_on_jupyter/app/contents/file/text-file.tsx
datalab_on_jupyter/app/styles/app.css
datalab_on_jupyter/app/styles/editor-overrides.css
datalab_on_jupyter/app/styles/global-variables.css
datalab_on_jupyter/app/triggers/open-notebook.ts
datalab_on_jupyter/dist/0-d8f287900dcae0f2896b.bundle.js
datalab_on_jupyter/dist/0-d8f287900dcae0f2896b.bundle.js.map
datalab_on_jupyter/dist/0-f50b4196cead3e5bb79a.bundle.js
datalab_on_jupyter/dist/0-f50b4196cead3e5bb79a.bundle.js.map
datalab_on_jupyter/dist/1-53484b9d4b6d3cd73e94.bundle.js
datalab_on_jupyter/dist/1-53484b9d4b6d3cd73e94.bundle.js.map
datalab_on_jupyter-2.2.1.dist-info/METADATA
datalab_on_jupyter-2.2.1.dist-info/WHEEL
datalab_on_jupyter-2.2.1.dist-info/entry_points.txt
datalab_on_jupyter-2.2.1.dist-info/top_level.txt
datalab_on_jupyter-2.2.1.dist-info/RECORD
